CHANGES.txt
README.txt
bootstrap.py
buildout.cfg
setup.py
src/zope/__init__.py
src/zope.app.externaleditor.egg-info/PKG-INFO
src/zope.app.externaleditor.egg-info/SOURCES.txt
src/zope.app.externaleditor.egg-info/dependency_links.txt
src/zope.app.externaleditor.egg-info/namespace_packages.txt
src/zope.app.externaleditor.egg-info/not-zip-safe
src/zope.app.externaleditor.egg-info/requires.txt
src/zope.app.externaleditor.egg-info/top_level.txt
src/zope/app/__init__.py
src/zope/app/externaleditor/MAINTAINER.txt
src/zope/app/externaleditor/SETUP.cfg
src/zope/app/externaleditor/__init__.py
src/zope/app/externaleditor/configure.zcml
src/zope/app/externaleditor/interfaces.py
src/zope/app/externaleditor/zope.app.externaleditor-configure.zcml
src/zope/app/externaleditor/browser/__init__.py
src/zope/app/externaleditor/tests/__init__.py
src/zope/app/externaleditor/tests/test_external_edit.py